{
  "id": "api-asapcomms_0",
  "text": "AsapComms\nType: API Documentation\nCategory: ['API']\nVersion: 23.3.3\nTags: AsapComms, GET, POST, Required Fields, Examples\n\nAPI AsapComms\nSee API Specification\n\nThe AsapComm table is used by the Web Sched ASAP feature to quickly send text messages to patients on the ASAP List about last minute appointment openings. See Web Sched ASAP, Web Sched ASAP History, and Web Sched ASAP: What Patient Sees for more information.\n\nAsapComms GET (single)\nVersion Added: 23.3.3\n\nGets a single asapcomm.\n\nParameters:\n\nAsapCommNum: Required in the URL.\n\nExample Request:\nGET /asapcomms/192\nRelated components:\n- references Unknown (db)\n- Unknown (db) referenced_by this\n- references Unknown (db)\n- Unknown (db) referenced_by this\n- references Unknown (db)\n- Unknown (db) referenced_by this\n- references Unknown (db)\n- Unknown (db) referenced_by this\n- references Unknown (db)\n- Unknown (db) referenced_by this\n- references Unknown (db)\n- Unknown (db) referenced_by this\n- references Unknown (db)\n- Unknown (db) referenced_by this\n",
  "metadata": {
    "id": "api-asapcomms",
    "title": "AsapComms",
    "type": "api",
    "entity_id": "api-asapcomms",
    "category": [
      "API"
    ],
    "version": "23.3.3",
    "filename": "api-asapcomms.json",
    "tags": [
      "AsapComms",
      "GET",
      "POST",
      "Required Fields",
      "Examples"
    ],
    "chunk_index": 0,
    "source_start": 0,
    "source_end": 577,
    "relationships": [
      {
        "relation_type": "references",
        "direction": "outgoing",
        "target_id": "db-patient",
        "target_name": "Unknown",
        "target_type": "db"
      },
      {
        "relation_type": "referenced_by",
        "direction": "incoming",
        "source_id": "db-patient",
        "source_name": "Unknown",
        "source_type": "db"
      },
      {
        "relation_type": "references",
        "direction": "outgoing",
        "target_id": "db-asapcomm",
        "target_name": "Unknown",
        "target_type": "db"
      },
      {
        "relation_type": "referenced_by",
        "direction": "incoming",
        "source_id": "db-asapcomm",
        "source_name": "Unknown",
        "source_type": "db"
      },
      {
        "relation_type": "references",
        "direction": "outgoing",
        "target_id": "db-operatory",
        "target_name": "Unknown",
        "target_type": "db"
      },
      {
        "relation_type": "referenced_by",
        "direction": "incoming",
        "source_id": "db-operatory",
        "source_name": "Unknown",
        "source_type": "db"
      },
      {
        "relation_type": "references",
        "direction": "outgoing",
        "target_id": "db-clinic",
        "target_name": "Unknown",
        "target_type": "db"
      },
      {
        "relation_type": "referenced_by",
        "direction": "incoming",
        "source_id": "db-clinic",
        "source_name": "Unknown",
        "source_type": "db"
      },
      {
        "relation_type": "references",
        "direction": "outgoing",
        "target_id": "db-document",
        "target_name": "Unknown",
        "target_type": "db"
      },
      {
        "relation_type": "referenced_by",
        "direction": "incoming",
        "source_id": "db-document",
        "source_name": "Unknown",
        "source_type": "db"
      },
      {
        "relation_type": "references",
        "direction": "outgoing",
        "target_id": "db-schedule",
        "target_name": "Unknown",
        "target_type": "db"
      },
      {
        "relation_type": "referenced_by",
        "direction": "incoming",
        "source_id": "db-schedule",
        "source_name": "Unknown",
        "source_type": "db"
      },
      {
        "relation_type": "references",
        "direction": "outgoing",
        "target_id": "db-appointment",
        "target_name": "Unknown",
        "target_type": "db"
      },
      {
        "relation_type": "referenced_by",
        "direction": "incoming",
        "source_id": "db-appointment",
        "source_name": "Unknown",
        "source_type": "db"
      }
    ]
  },
  "embedding": [
    0.0017590859206393361,
    0.030604679137468338,
    0.0036799681838601828,
    -0.025614161044359207,
    -0.014453807845711708,
    0.022637108340859413,
    -0.005896578077226877,
    -0.013468647375702858,
    0.0041563683189451694,
    -0.007226903922855854,
    0.006799042224884033,
    -0.008679475635290146,
    0.0013204379938542843,
    0.0174883883446455,
    -0.018912196159362793,
    0.007830943912267685,
    0.011951357126235962,
    -0.016237162053585052,
    0.007759034167975187,
    0.002831436228007078,
    0.0016296488465741277,
    0.031697701662778854,
    0.013497411273419857,
    0.027857735753059387,
    -0.00891677662730217,
    0.008370264433324337,
    -0.010239911265671253,
    -0.014094260521233082,
    -0.023500021547079086,
    -0.006216575391590595,
    0.01155585516244173,
    -0.02962671034038067,
    -0.007345554418861866,
    -0.03434397280216217,
    0.021889248862862587,
    0.008269591256976128,
    0.005314111243933439,
    0.01663985662162304,
    0.028044700622558594,
    -0.021371500566601753,
    -0.005979273933917284,
    -0.012677643448114395,
    0.008585993200540543,
    0.00801071710884571,
    -0.0009065089980140328,
    -0.006320844404399395,
    0.02360069379210472,
    -0.05042293295264244,
    0.01685558445751667,
    0.009182841517031193,
    -0.014971556141972542,
    0.01705693081021309,
    -0.04320322349667549,
    -0.008708239533007145,
    0.012936517596244812,
    0.015690650790929794,
    0.048006776720285416,
    0.037738099694252014,
    -0.019070396199822426,
    0.015546832233667374,
    0.025312140583992004,
    -0.015532449819147587,
    -0.0219036303460598,
    0.016237162053585052,
    -0.02493821084499359,
    0.001118192565627396,
    -0.037594281136989594,
    0.010549122467637062,
    -0.0003168511902913451,
    -0.006540168076753616,
    0.02942536398768425,
    0.01987578347325325,
    0.002144700614735484,
    -0.020407913252711296,
    0.007198140025138855,
    -0.022363850846886635,
    -0.014957173727452755,
    0.00025527869001962245,
    -0.00944171566516161,
    -0.0020656001288443804,
    0.0060188244096934795,
    -0.007528923451900482,
    -0.0037392934318631887,
    0.016754910349845886,
    0.02211936004459858,
    0.002973457332700491,
    0.0026318873278796673,
    0.03995291143655777,
    -0.008808912709355354,
    -0.01102372445166111,
    0.008248018100857735,
    0.016107724979519844,
    0.006220170762389898,
    0.013367974199354649,
    0.009837218560278416,
    0.021170154213905334,
    -0.015748178586363792,
    0.05226381868124008,
    0.0035001945216208696,
    -0.007981953211128712,
    0.002486270619556308,
    0.019631290808320045,
    0.004850294906646013,
    -0.009434524923563004,
    -0.020048364996910095,
    0.014417853206396103,
    0.020522968843579292,
    0.005324897821992636,
    0.02050858736038208,
    -0.0023496425710618496,
    -0.0022345874458551407,
    0.037392936646938324,
    -0.004853890743106604,
    -0.0041851322166621685,
    0.02155846543610096,
    -0.018293773755431175,
    0.0219036303460598,
    -0.036472491919994354,
    -0.026246963068842888,
    -0.02331305667757988,
    -0.01889781467616558,
    0.04423872008919716,
    0.030719734728336334,
    -0.023974623531103134,
    0.013856958597898483,
    0.020307239145040512,
    -0.04222525283694267,
    -0.0023802041541785,
    -0.017948608845472336,
    -0.008097008801996708,
    0.030949844047427177,
    0.0050875963643193245,
    0.029684238135814667,
    0.035925980657339096,
    -0.016337836161255836,
    0.011613382957875729,
    -0.005716804414987564,
    0.03457408398389816,
    -0.017301423475146294,
    -0.023974623531103134,
    0.04093088209629059,
    0.041333574801683426,
    -0.010772041976451874,
    0.025786742568016052,
    0.010189575143158436,
    -0.00043909731903113425,
    0.031093664467334747,
    -0.025197084993124008,
    -0.039780329912900925,
    -0.019358035176992416,
    0.03624238446354866,
    0.011002152226865292,
    -0.0017276254948228598,
    0.00043617599294520915,
    -0.014612008817493916,
    -0.00349300354719162,
    -0.005623321980237961,
    0.04633847624063492,
    -0.006540168076753616,
    -0.01819310151040554,
    -0.039837855845689774,
    0.0238739512860775,
    0.003804011968895793,
    -0.01966005377471447,
    0.029799291864037514,
    0.02296789176762104,
    -0.01103091612458229,
    -0.014245269820094109,
    -0.03143882751464844,
    -0.01316662784665823,
    0.00450872490182519,
    -0.006011633202433586,
    0.02492382936179638,
    -0.007881280034780502,
    -0.0019271743949502707,
    0.003832775866612792,
    0.003958617337048054,
    -0.03083479031920433,
    0.008276781998574734,
    -0.014029541984200478,
    -0.025959325954318047,
    0.02653460204601288,
    0.036472491919994354,
    0.05119955539703369,
    -0.023643840104341507,
    0.005493884906172752,
    0.003248511115089059,
    0.01158461906015873,
    0.01797737181186676,
    -0.012368432246148586,
    0.019056014716625214,
    0.00849251076579094,
    0.02738313376903534,
    -0.013547748327255249,
    -0.5214300751686096,
    -0.022737780585885048,
    -0.003645811229944229,
    0.014302797615528107,
    0.029741765931248665,
    0.0016853787237778306,
    0.018020518124103546,
    -0.008017907850444317,
    -0.02135711908340454,
    0.029540417715907097,
    -0.011620573699474335,
    0.0003833674709312618,
    0.0030166031792759895,
    -0.003198174526914954,
    -0.00849251076579094,
    -0.011455181986093521,
    0.013001236133277416,
    -0.010944624431431293,
    0.03428644314408302,
    -0.009470479562878609,
    -0.01714322157204151,
    -0.0023011036682873964,
    -0.010836760513484478,
    0.023126091808080673,
    0.010692941024899483,
    -0.004638161975890398,
    -1.5140318282647058e-05,
    -0.009628680534660816,
    -0.01404392346739769,
    0.01313786394894123,
    -0.037881918251514435,
    0.026851003989577293,
    0.005605344660580158,
    -0.025729214772582054,
    0.03333723917603493,
    0.02121330052614212,
    -0.020393531769514084,
    0.004124009050428867,
    0.014856500551104546,
    0.019012868404388428,
    -0.01960252784192562,
    -0.0008026896975934505,
    0.016107724979519844,
    -0.01517290249466896,
    -0.03316465765237808,
    -0.013130673207342625,
    0.0032233428210020065,
    -0.0079675717279315,
    -0.009003068320453167,
    -0.03474666550755501,
    0.013612466864287853,
    0.007643979042768478,
    -0.016165252774953842,
    0.012167085893452168,
    0.003061546478420496,
    0.029971875250339508,
    0.01825062930583954,
    0.0070435344241559505,
    -0.009607108309864998,
    0.0076799336820840836,
    -0.003962212707847357,
    -0.00043123221257701516,
    -0.039722803980112076,
    -0.03428644314408302,
    -0.02142902836203575,
    0.0460796020925045,
    0.0032628930639475584,
    -0.005907364655286074,
    0.012210231274366379,
    0.006403540261089802,
    0.016668619588017464,
    0.04208143427968025,
    0.007953189313411713,
    0.01615087129175663,
    0.009679017588496208,
    0.004012549761682749,
    0.017186367884278297,
    -0.002941098064184189,
    0.0037860346492379904,
    0.010534740053117275,
    -0.0035756994038820267,
    -0.001955938059836626,
    0.0066048866137862206,
    -0.03799697384238243,
    0.00033213195274583995,
    0.012584161013364792,
    -0.04593578353524208,
    -0.03273319825530052,
    0.0009519018931314349,
    -0.0005793208256363869,
    0.021544083952903748,
    0.03385498747229576,
    0.0012440341524779797,
    0.006335225887596607,
    0.006399944424629211,
    0.022709017619490623,
    0.0020620045252144337,
    0.010692941024899483,
    0.001546952873468399,
    -0.017891081050038338,
    0.023399347439408302,
    -0.033739931881427765,
    0.009405761025846004,
    0.020767461508512497,
    0.0023945861030369997,
    -0.026721566915512085,
    -0.014345942996442318,
    -0.022220032289624214,
    0.021731048822402954,
    -0.023917095735669136,
    -0.00654735928401351,
    -0.03161141276359558,
    0.015705032274127007,
    -0.0020368362311273813,
    -0.03411386162042618,
    -0.03535070642828941,
    0.01656794734299183,
    0.018984105437994003,
    0.025225849822163582,
    0.0024089678190648556,
    -0.020105892792344093,
    -0.0073563409969210625,
    0.005885791964828968,
    0.008665093220770359,
    0.03132377564907074,
    0.015331103466451168,
    0.012224613688886166,
    0.008837676607072353,
    -0.004832317586988211,
    -0.00919722393155098,
    0.01812119223177433,
    -0.022220032289624214,
    0.018293773755431175,
    -0.010031374171376228,
    0.028274811804294586,
    -0.028778178617358208,
    -0.0028601998928934336,
    -0.0008381949737668037,
    0.008521274663507938,
    -0.03089231625199318,
    0.006752301007509232,
    -0.014101451262831688,
    0.008348692208528519,
    0.0015487506752833724,
    -0.0056952317245304585,
    -0.0026300896424800158,
    -0.02521146647632122,
    0.02478001080453396,
    0.00207998207770288,
    0.01790546253323555,
    0.00891677662730217,
    -0.019962074235081673,
    -0.012612924911081791,
    0.0012377421371638775,
    0.008600374683737755,
    -0.03322218358516693,
    -0.01323853712528944,
    -0.020192185416817665,
    -0.008434982970356941,
    -0.011649337597191334,
    0.002903345739468932,
    0.01193697564303875,
    -0.02043667621910572,
    -0.006651627831161022,
    0.006586909294128418,
    -0.008334309794008732,
    -0.04797801002860069,
    0.008197681978344917,
    -0.011570236645638943,
    -0.007730270270258188,
    -0.02794402837753296,
    -0.018293773755431175,
    -0.008542847819626331,
    0.041419867426157,
    -0.04150615632534027,
    0.012354050762951374,
    -0.012095176614820957,
    -0.0003667383862193674,
    0.03253185376524925,
    0.005188269540667534,
    -0.022234413772821426,
    0.009930700995028019,
    0.0027757063508033752,
    -0.004954563919454813,
    0.024060916155576706,
    0.0001971893070731312,
    0.022090595215559006,
    0.010685750283300877,
    -0.01323853712528944,
    0.018552647903561592,
    -0.034228917211294174,
    0.02606000006198883,
    -0.02564292401075363,
    0.04067200794816017,
    -0.02007712982594967,
    0.01777602545917034,
    0.006069160997867584,
    0.04311693087220192,
    0.004289401229470968,
    0.009434524923563004,
    0.0019343652529641986,
    -0.010664177127182484,
    0.038169559091329575,
    -0.007392295636236668,
    -0.005986465141177177,
    -0.011577428318560123,
    0.027282459661364555,
    -0.00944171566516161,
    0.017100077122449875,
    -0.006741514895111322,
    0.012864607386291027,
    0.006838592700660229,
    -0.005360852461308241,
    -0.0022939126938581467,
    0.020048364996910095,
    -0.011081252247095108,
    0.005982869770377874,
    0.01039811223745346,
    -0.019717581570148468,
    0.002047622809186578,
    0.025182703509926796,
    0.005839050747454166,
    0.02774268202483654,
    -0.020134657621383667,
    -0.023399347439408302,
    0.01770411618053913,
    0.022838454693555832,
    0.014051114208996296,
    4.9522044719196856e-05,
    -0.0547950305044651,
    -0.032129161059856415,
    0.01397201418876648,
    0.01825062930583954,
    0.013741903938353062,
    0.03207163140177727,
    0.00821925513446331,
    0.015834469348192215,
    -0.01228933222591877,
    0.01298685371875763,
    0.0034103074576705694,
    -0.011160353198647499,
    0.019271742552518845,
    -0.006759492214769125,
    -0.015359867364168167,
    -0.0020530158653855324,
    -0.0008152738446369767,
    0.011469563469290733,
    0.036760132759809494,
    0.02309732884168625,
    -0.0020871730521321297,
    -0.0058174775913357735,
    0.026922913268208504,
    -0.017042549327015877,
    0.026793476194143295,
    -0.001317741465754807,
    0.026074381545186043,
    -0.00449434295296669,
    0.012274949811398983,
    0.026865385472774506,
    0.019343653693795204,
    0.018423210829496384,
    -0.003512778552249074,
    0.020264094695448875,
    0.023082945495843887,
    -0.009837218560278416,
    0.007521732710301876,
    0.007126230280846357,
    -0.02197553962469101,
    -0.005421975627541542,
    -0.04018302261829376,
    0.023989005014300346,
    -0.017819171771407127,
    -0.00013247077004052699,
    -0.034861721098423004,
    0.016467273235321045,
    -0.0005249392706900835,
    -0.004008953925222158,
    7.112298044376075e-05,
    0.025815507397055626,
    0.0031712085474282503,
    -0.006234552711248398,
    -0.05772893875837326,
    0.02962671034038067,
    0.0007959481445141137,
    -0.012087984941899776,
    0.001269202446565032,
    0.026879766955971718,
    0.021472174674272537,
    -0.02246452495455742,
    0.01295808982104063,
    -0.018768377602100372,
    -0.01520166639238596,
    -0.008557229302823544,
    0.013569320552051067,
    -0.0010319012217223644,
    -0.008873631246387959,
    0.044411301612854004,
    0.00987317319959402,
    -0.017502769827842712,
    0.0018094225088134408,
    -0.019818255677819252,
    0.010009801015257835,
    -0.04147739335894585,
    -0.008312736637890339,
    0.0250101201236248,
    0.025455959141254425,
    -0.014719872735440731,
    -0.036127328872680664,
    -0.000968081527389586,
    -0.028691885992884636,
    1.5435260138474405e-05,
    -0.03385498747229576,
    -0.015906378626823425,
    -0.017502769827842712,
    0.012217422015964985,
    -0.011793156154453754,
    -0.04950249195098877,
    0.011994502507150173,
    0.021817339584231377,
    -0.040499426424503326,
    0.004548275377601385,
    -0.0282316654920578,
    -0.011081252247095108,
    0.03267567232251167,
    0.018710849806666374,
    -0.011390463449060917,
    0.02037915028631687,
    -0.009671826846897602,
    -0.009707781486213207,
    0.014856500551104546,
    -0.014985937625169754,
    -0.001004036283120513,
    -0.011447991244494915,
    -0.016726147383451462,
    0.01734456978738308,
    0.0031046923249959946,
    0.04081582650542259,
    -0.011785965412855148,
    0.037105295807123184,
    0.028619976714253426,
    -0.012994044460356236,
    -0.007104657590389252,
    0.005752759054303169,
    -0.02444922737777233,
    -0.011606191284954548,
    -0.04374973475933075,
    -0.005910960026085377,
    0.018567031249403954,
    0.05321302264928818,
    -0.0076511697843670845,
    0.002959075616672635,
    -0.007000389043241739,
    -0.007108252961188555,
    -0.016251545399427414,
    -0.021011952310800552,
    0.01699940301477909,
    0.038198322057724,
    -0.010297439061105251,
    0.006540168076753616,
    0.012720788829028606,
    0.01768973469734192,
    -0.0079388078302145,
    -0.01790546253323555,
    0.00768712442368269,
    0.04003920406103134,
    0.021328354254364967,
    0.021874867379665375,
    -0.010239911265671253,
    -0.0004094346659258008,
    -0.00423187343403697,
    -0.004515916109085083,
    0.018063664436340332,
    0.021687902510166168,
    -0.010110474191606045,
    0.014281224459409714,
    0.0016422329936176538,
    -0.00016033569409046322,
    0.0028961547650396824,
    -0.0018624557415023446,
    0.028778178617358208,
    -0.00919722393155098,
    0.017042549327015877,
    -0.045964546501636505,
    -0.015546832233667374,
    -0.013425501994788647,
    0.007129826117306948,
    0.005889387335628271,
    -0.0033833414781838655,
    -0.028130993247032166,
    -0.02716740593314171,
    -0.047517791390419006,
    -0.003341993549838662,
    -0.004544680006802082,
    -0.005835454910993576,
    -0.009463288821280003,
    -0.011886638589203358,
    0.00415996415540576,
    0.0030957036651670933,
    0.011009342968463898,
    -0.015029083006083965,
    0.018984105437994003,
    0.0062669119797647,
    -0.003110085381194949,
    0.034228917211294174,
    -0.014985937625169754,
    -0.015891997143626213,
    0.00028539079357869923,
    -0.009743736125528812,
    0.006097924895584583,
    -0.0174883883446455,
    0.04199514165520668,
    -0.0037536753807216883,
    -0.014870882965624332,
    0.023701367899775505,
    0.0027757063508033752,
    0.011455181986093521,
    -0.006353203672915697,
    -0.003688956843689084,
    0.0175459161400795,
    0.015633122995495796,
    0.0325893796980381,
    0.0025132365990430117,
    -0.029022669419646263,
    0.014489762485027313,
    -0.001063361531123519,
    -0.01799175515770912,
    -0.0111315893009305,
    0.001808523666113615,
    -0.00042111994116567075,
    0.011225071735680103,
    0.019545000046491623,
    0.05030788108706474,
    -0.008701047860085964,
    -0.01721513271331787,
    -0.013461456634104252,
    0.00909655075520277,
    -0.004418838303536177,
    -0.022694634273648262,
    0.02016342058777809,
    0.021011952310800552,
    -0.0076511697843670845,
    -0.020307239145040512,
    0.0027397514786571264,
    -0.020609259605407715,
    0.02175981178879738,
    -0.03543699532747269,
    -0.01175720151513815,
    0.00573837710544467,
    -0.020307239145040512,
    0.02296789176762104,
    -0.017114458605647087,
    -0.04579196497797966,
    0.014259652234613895,
    -0.001586503116413951,
    0.005616131238639355,
    -0.011347317136824131,
    0.011347317136824131,
    0.02836110256612301,
    -0.016553563997149467,
    -0.004695689771324396,
    -0.0028763795271515846,
    0.0333084762096405,
    0.010419685393571854,
    -0.004257041960954666,
    -0.00839183758944273,
    0.010462830774486065,
    -0.03601227328181267,
    0.025240231305360794,
    -0.013360783457756042,
    -0.025815507397055626,
    -0.011340126395225525,
    -0.030230749398469925,
    -0.0019936906173825264,
    0.020882515236735344,
    0.01200888492166996,
    0.020594878122210503,
    -0.009923509322106838,
    -0.03727788105607033,
    -0.01602143421769142,
    -0.010362157598137856,
    0.0032413203734904528,
    0.0007429149118252099,
    0.018078045919537544,
    0.01158461906015873,
    0.04872586950659752,
    -0.0013465052470564842,
    0.0033078365959227085,
    0.01517290249466896,
    0.012087984941899776,
    0.021170154213905334,
    0.008866440504789352,
    -0.023989005014300346,
    0.014612008817493916,
    0.034948013722896576,
    0.0066048866137862206,
    0.03089231625199318,
    0.032474324107170105,
    0.029123343527317047,
    -0.00670555979013443,
    0.023428112268447876,
    0.026376400142908096,
    0.002364024519920349,
    0.0031801972072571516,
    -0.03699024021625519,
    0.020537350326776505,
    -0.017330186441540718,
    -0.005867814179509878,
    0.003672777209430933,
    -0.06949333101511002,
    -0.008708239533007145,
    -0.00891677662730217,
    0.01902725175023079,
    -0.022809689864516258,
    -0.00022336885740514845,
    0.020824987441301346,
    -0.0037105297669768333,
    0.03707653284072876,
    -0.015604359097778797,
    0.036760132759809494,
    -0.035091832280159,
    -0.005332088563591242,
    -0.019185451790690422,
    -0.037191588431596756,
    0.006000847090035677,
    0.010261484421789646,
    0.01875399425625801,
    0.040902119129896164,
    -0.0035109808668494225,
    0.00014168416964821517,
    -0.00043909731903113425,
    -0.03256061673164368,
    -0.03313589468598366,
    -0.010843951255083084,
    0.031697701662778854,
    0.0013195391511544585,
    -0.008866440504789352,
    -0.006475449539721012,
    -0.023327438160777092,
    -0.0009959464659914374,
    0.012296522967517376,
    0.029799291864037514,
    0.026577748358249664,
    -0.010800805874168873,
    -0.0028134589083492756,
    0.007090275641530752,
    -0.04907103627920151,
    -0.005806691478937864,
    -0.0011613382957875729,
    0.023830804973840714,
    0.012735170312225819,
    -0.01390010491013527,
    -0.00450872490182519,
    -0.020048364996910095,
    -0.022277560085058212,
    0.00891677662730217,
    0.007881280034780502,
    0.04628094658255577,
    0.004925800021737814,
    0.003872326109558344,
    0.02732560597360134,
    0.016553563997149467,
    -0.03615609183907509,
    -0.04492904990911484,
    0.02493821084499359,
    0.016740528866648674,
    0.018638940528035164,
    -0.03166893869638443,
    -0.0034786215983331203,
    -0.0054327622056007385,
    0.031870286911726,
    -0.019688818603754044,
    -0.024765629321336746,
    0.04584949091076851,
    0.008701047860085964,
    -0.002198632573708892,
    -0.010944624431431293,
    0.00022100932255852968,
    0.019487472251057625,
    0.01721513271331787,
    0.008305545896291733,
    0.013475838117301464,
    -0.013317637145519257,
    -0.015906378626823425,
    -0.0022094191517680883,
    -0.011599000543355942,
    0.017747262492775917,
    0.002897952450439334,
    0.011922593228518963,
    0.008959922939538956,
    0.031496357172727585,
    0.03141006454825401,
    -0.008952731266617775,
    -0.014317179098725319,
    0.034660372883081436,
    -0.035925980657339096,
    -0.01571941375732422,
    0.002766717690974474,
    0.0041815368458628654,
    -0.012591351754963398,
    0.014626390300691128,
    -0.03854348510503769,
    0.01175720151513815,
    -0.020609259605407715,
    -0.0174883883446455,
    0.00064089335501194,
    0.016798056662082672,
    -0.006694773677736521,
    -0.01902725175023079,
    0.008981495164334774,
    -0.010944624431431293,
    -0.021170154213905334,
    -0.004710071720182896,
    0.022910363972187042,
    -0.029597945511341095,
    0.004152772948145866,
    -0.039722803980112076,
    -0.0056952317245304585,
    0.02801593765616417,
    0.014712681993842125,
    0.008341500535607338,
    0.010930242948234081,
    0.017373332753777504,
    -0.017517151311039925,
    0.01025429368019104,
    -0.01190821174532175,
    0.025168322026729584,
    -0.016093343496322632,
    0.013957631774246693,
    0.0038867080584168434,
    -0.012771125882863998,
    0.02626134641468525,
    0.01825062930583954,
    -0.01888343133032322,
    -0.041333574801683426,
    -0.010124856606125832,
    -0.005145124159753323,
    0.0042067053727805614,
    0.004289401229470968,
    0.03601227328181267,
    0.01937241666018963,
    -0.0051127648912370205,
    -0.0017060526879504323,
    0.005849836859852076,
    0.01636659912765026,
    0.008729811757802963,
    -0.004587825387716293,
    0.04052818939089775,
    -0.014288416132330894,
    0.024981357157230377,
    -0.015403012745082378,
    -0.018480738624930382,
    0.02121330052614212,
    -0.033049602061510086,
    -0.018020518124103546,
    -0.02472248300909996,
    -0.023758895695209503,
    0.0033078365959227085,
    -0.013792240060865879,
    -0.05304044112563133,
    -0.02007712982594967,
    -0.00877295807003975,
    0.05700984224677086,
    0.012541014701128006,
    0.0023963837884366512,
    -0.007018366362899542,
    0.003541542449966073,
    0.004098840989172459,
    0.025240231305360794,
    -0.013806622475385666,
    0.008305545896291733,
    -0.004221086855977774,
    -0.0027721107471734285,
    -0.01404392346739769,
    -0.015705032274127007,
    0.011102825403213501,
    0.02836110256612301,
    -0.006565336603671312,
    -0.02866312302649021,
    -0.03365364298224449,
    -0.01861017569899559,
    -0.06023138761520386,
    -0.013634039089083672,
    -0.05246516317129135,
    0.017891081050038338,
    0.002734358422458172,
    0.018020518124103546,
    0.009542389772832394,
    0.007521732710301876,
    -0.009851600043475628,
    -0.023471256718039513,
    -0.04262794554233551,
    0.024736864492297173,
    -0.0039154719561338425,
    0.0016215590294450521,
    0.02042229473590851,
    -0.010239911265671253,
    -0.03822708502411842,
    -0.001269202446565032,
    0.019832637161016464,
    0.0014022350078448653,
    0.018638940528035164,
    0.015460540540516376,
    0.028778178617358208,
    -0.0008521274430677295,
    -0.0015712223248556256,
    -0.021788574755191803,
    -0.035494524985551834,
    -0.003030985128134489,
    -0.003750080009922385,
    -0.024636192247271538,
    -0.011577428318560123,
    0.0027091901283711195,
    5.5280419474001974e-05,
    0.034660372883081436,
    0.010441257618367672,
    0.009750926867127419,
    0.006360394414514303,
    0.013741903938353062,
    -0.01944432593882084,
    -0.007061511743813753,
    -0.0005051641492173076,
    0.01243315078318119,
    0.032618146389722824,
    0.008485320024192333,
    0.0023136879317462444,
    0.014712681993842125,
    0.008751384913921356,
    0.012282140552997589,
    -0.008650711737573147,
    0.015230430290102959,
    -0.03811202943325043,
    0.01341111958026886,
    0.014403470791876316,
    0.009074977599084377,
    -0.03356735035777092,
    -0.031093664467334747,
    -0.005012091249227524,
    0.00821206346154213,
    -0.018926577642560005,
    0.010872715152800083,
    0.0051127648912370205,
    -0.037536755204200745,
    0.009261942468583584,
    0.006996793206781149,
    -0.03477542847394943,
    -0.023212382569909096,
    -0.006202193442732096,
    -0.0013456062879413366,
    -0.01218865904957056,
    -0.01636659912765026,
    -0.004034122452139854,
    0.0029321094043552876,
    -0.031870286911726,
    0.01931488886475563,
    -0.009988227859139442,
    -0.042743001133203506,
    0.031783994287252426,
    0.008859248831868172,
    -0.011670909821987152,
    0.005353661719709635,
    0.20134657621383667,
    -0.016539182513952255,
    -0.01537424884736538,
    0.0019972859881818295,
    -0.0077949888072907925,
    -0.010728895664215088,
    -0.02302541956305504,
    0.015705032274127007,
    -0.019545000046491623,
    0.02590179815888405,
    -0.003629631595686078,
    -0.022263178601861,
    0.02745504304766655,
    0.011843493208289146,
    0.004724453669041395,
    -0.010692941024899483,
    -0.015474922023713589,
    -0.012727979570627213,
    -0.03474666550755501,
    -0.01763220690190792,
    0.0003166264796163887,
    -0.02318361960351467,
    0.022924745455384254,
    0.0009986429940909147,
    0.025959325954318047,
    0.0034822169691324234,
    -0.0007074096356518567,
    -0.006975220516324043,
    0.03937763720750809,
    -0.0018229056149721146,
    -0.012850225903093815,
    -0.0046489485539495945,
    0.012670451775193214,
    0.01218865904957056,
    -0.03307836502790451,
    -0.024204734712839127,
    -0.001173922442831099,
    4.011201235698536e-05,
    0.011929783970117569,
    0.045187924057245255,
    -0.03083479031920433,
    -0.026218200102448463,
    0.02513955719769001,
    -0.048064302653074265,
    0.024190353229641914,
    -0.01636659912765026,
    0.00458423001691699,
    -0.023830804973840714,
    -0.020839370787143707,
    0.0036350246518850327,
    -0.04024055227637291,
    0.029741765931248665,
    0.009190033189952374,
    -0.006644437089562416,
    -0.010520358569920063,
    -0.04242660105228424,
    0.005968487821519375,
    -0.004102436359971762,
    0.0035954744089394808,
    0.017171986401081085,
    -0.007223308086395264,
    0.019142305478453636,
    -0.011390463449060917,
    0.00863632932305336,
    -0.010484403930604458,
    0.013274491764605045,
    0.0019109947606921196,
    -0.012267759069800377,
    0.015978287905454636,
    -0.0021464983001351357,
    -0.007273645140230656,
    0.001295269699767232,
    -0.02331305667757988,
    -0.010937433689832687,
    -0.016237162053585052,
    0.0001464032247895375,
    0.006471854168921709,
    0.021055098623037338,
    0.02423349767923355,
    0.029741765931248665,
    -0.024190353229641914,
    -0.0015936940908432007,
    -0.014274033717811108,
    0.016481654718518257,
    0.007665551733225584,
    0.007050725631415844,
    0.02121330052614212,
    -0.032186686992645264,
    -0.030086930841207504,
    -0.002067397814244032,
    -0.0002303350920556113,
    0.0015406608581542969,
    -0.014029541984200478,
    -0.002842222573235631,
    0.006493426859378815,
    -0.002986041596159339,
    -0.005411189049482346,
    0.004314569290727377,
    0.007924425415694714,
    0.029741765931248665,
    -0.004641757812350988,
    0.08911024034023285,
    -0.007802179548889399,
    -0.009664635173976421,
    -0.013533365912735462,
    -0.023442493751645088,
    -0.007593641988933086,
    0.03376869484782219,
    -0.01130417175590992,
    -0.004073672462254763,
    -0.027411898598074913,
    -0.02788650058209896,
    -0.007363531738519669,
    -0.0076511697843670845,
    -0.01075046882033348,
    0.025873035192489624,
    0.006403540261089802,
    -0.013713140040636063,
    0.015877615660429,
    -0.024909447878599167,
    -0.02007712982594967,
    -0.017358951270580292,
    0.0028799751307815313,
    -0.01085114199668169,
    -0.019199833273887634,
    -0.014166169799864292,
    -0.017531532794237137,
    -0.026879766955971718,
    0.008600374683737755,
    -0.023830804973840714,
    0.02801593765616417,
    0.032963309437036514,
    0.015705032274127007,
    0.030432095751166344,
    -0.030288277193903923,
    0.021040717139840126,
    -0.00023685187625233084,
    -0.03604103624820709,
    -0.03221544995903969,
    0.002403574762865901,
    0.04003920406103134,
    -0.01902725175023079,
    0.010585077106952667,
    -0.006957243196666241,
    0.05033664405345917,
    -0.03834214061498642,
    0.01705693081021309,
    0.005803095642477274,
    -0.009154078550636768,
    -0.012684834189713001,
    0.005101978313177824,
    -0.005684445146471262,
    0.03871607035398483,
    -0.020824987441301346,
    0.023787658661603928,
    0.01721513271331787,
    -0.00165481714066118,
    -0.022421378642320633,
    -0.005159506108611822,
    -0.012677643448114395,
    -0.011771583929657936,
    -0.02738313376903534,
    0.03166893869638443,
    0.005882196128368378,
    -0.023773277178406715,
    -0.012425960041582584,
    -0.1810968667268753,
    0.025527868419885635,
    -0.0023244742769747972,
    0.012994044460356236,
    0.01692749373614788,
    -0.0015083015896379948,
    0.016452891752123833,
    0.010232720524072647,
    -0.0055262441746890545,
    -0.0031082876957952976,
    0.015230430290102959,
    -0.04205267131328583,
    -0.011548664420843124,
    0.005148719530552626,
    0.028821323066949844,
    -0.005655681248754263,
    -0.013957631774246693,
    0.013785049319267273,
    0.024463608860969543,
    0.010160811245441437,
    0.017847934737801552,
    0.008514083921909332,
    0.00512714684009552,
    0.009758117608726025,
    -0.004907822702080011,
    0.009211605414748192,
    -0.014957173727452755,
    0.024607427418231964,
    -0.007327577099204063,
    -0.017387714236974716,
    -0.030777262523770332,
    -0.015518068335950375,
    0.02900828793644905,
    -0.006464662961661816,
    -0.01783355325460434,
    -0.007536114659160376,
    -0.005928937345743179,
    0.013008426874876022,
    -0.023399347439408302,
    0.020479822531342506,
    -0.008600374683737755,
    0.043145693838596344,
    -0.006008037831634283,
    -0.014576053246855736,
    -0.014957173727452755,
    -0.004141986835747957,
    0.04803553968667984,
    -0.012116748839616776,
    0.005501076113432646,
    -0.038025736808776855,
    0.0033797461073845625,
    -0.059656113386154175,
    -0.014475380070507526,
    -0.004692094400525093,
    0.010390921495854855,
    0.030719734728336334,
    -0.01397201418876648,
    -0.0077949888072907925,
    -0.020479822531342506,
    -0.0027900882996618748,
    0.00909655075520277,
    -0.0038867080584168434,
    -0.013231346383690834,
    0.005292538553476334,
    -0.001455268356949091,
    -0.02991434745490551,
    -0.026390783488750458,
    0.027368752285838127,
    -0.0270379688590765,
    0.023715749382972717,
    -0.033049602061510086,
    0.020192185416817665,
    -0.021716665476560593,
    -0.014065496623516083,
    0.030432095751166344,
    -0.015748178586363792,
    -0.028533685952425003,
    0.047287680208683014,
    0.008787339553236961,
    0.01377066783607006,
    0.012346859090030193,
    0.03805450350046158,
    -0.00023932376643642783,
    -0.00017977372044697404,
    0.012440341524779797,
    0.011160353198647499,
    -0.0064287083223462105,
    0.01671176590025425,
    0.04438253864645958,
    -0.010088901035487652,
    0.004918609280139208,
    -0.04438253864645958,
    0.021457791328430176,
    0.01200888492166996,
    0.00669117784127593,
    0.040067967027425766,
    -0.023226765915751457,
    0.0004346029891166836,
    0.0238164234906435,
    -0.03756551817059517,
    0.005418380256742239,
    0.005324897821992636,
    0.0025977303739637136,
    0.021889248862862587,
    -0.028418630361557007,
    0.002195037202909589,
    -0.043577149510383606,
    -0.0026049213483929634,
    0.02331305667757988,
    -0.005619726609438658,
    -0.0013869543327018619,
    0.007615215145051479,
    0.007492968812584877,
    0.04150615632534027,
    0.009844409301877022,
    -0.010124856606125832,
    -0.004098840989172459,
    -0.021515319123864174,
    -0.011225071735680103,
    0.01366280298680067,
    0.059023309499025345,
    5.962026989436708e-06,
    -0.021745430305600166,
    -0.0031208719592541456,
    -0.01741647906601429,
    -0.0011766190873458982,
    -0.06811267137527466,
    -0.00029190757777541876,
    0.021328354254364967,
    0.053903352469205856,
    -0.00768712442368269,
    -0.004889845382422209,
    0.009233178570866585,
    -0.0041887275874614716,
    -0.0013941451907157898,
    0.02515394054353237,
    -0.04530297964811325,
    -0.023500021547079086,
    -0.01151270978152752,
    -0.01341111958026886,
    0.030604679137468338,
    0.020393531769514084,
    -0.02423349767923355,
    -0.029094580560922623,
    -0.014655154198408127,
    0.028893232345581055,
    -0.009923509322106838,
    -0.018006136640906334,
    -0.01607896201312542,
    -0.01761782541871071,
    -0.028619976714253426,
    0.0006157250027172267,
    -0.011095634661614895,
    0.023989005014300346,
    0.013849767856299877,
    0.007007579784840345,
    0.020479822531342506,
    -0.022248797118663788,
    0.011922593228518963,
    -0.015848850831389427,
    -0.005608940031379461,
    -0.006928479298949242,
    -0.04078706353902817,
    -0.003162219887599349,
    0.017718497663736343,
    -0.01622278057038784,
    -0.01386414933949709,
    0.011433608829975128,
    -0.026290109381079674,
    -0.036760132759809494,
    -0.013231346383690834,
    -0.02423349767923355,
    -0.019286125898361206,
    0.03207163140177727,
    0.006662414409220219,
    -0.019329270347952843,
    -0.003525362815707922,
    0.014784591272473335,
    -0.020451059564948082,
    -0.0070363436825573444,
    0.02050858736038208,
    -0.006374776363372803,
    0.01881152205169201,
    -0.0033833414781838655,
    -0.004296591971069574,
    -0.010196765884757042,
    -0.005590962711721659,
    -0.013583702966570854,
    -0.011649337597191334,
    0.032618146389722824,
    0.025614161044359207,
    -0.01151270978152752,
    0.009046213701367378,
    -0.005659277085214853,
    0.022277560085058212,
    -0.0018732422031462193,
    -0.03069096989929676,
    0.02268025279045105,
    -0.007751842960715294,
    -0.01678367517888546,
    -0.0093698063865304,
    -0.0005910061299800873,
    0.013274491764605045,
    -0.011138780042529106,
    0.016208399087190628,
    0.009348234161734581,
    -0.015216047875583172,
    -0.020407913252711296,
    -0.014942792244255543,
    0.0067487056367099285,
    0.015230430290102959,
    0.027196168899536133,
    0.004026931244879961,
    -0.01281427126377821,
    -0.013281682506203651,
    -0.05560041964054108,
    -5.615119880530983e-05,
    0.022450143471360207,
    0.02738313376903534,
    -0.004447602201253176,
    -0.017718497663736343,
    0.011268217116594315,
    0.016683001071214676,
    -0.0046525439247488976,
    0.0023442492820322514,
    0.011153161525726318,
    -0.044066134840250015,
    -0.003194579156115651,
    -0.08974304050207138,
    0.010671368800103664,
    0.0050840009935200214,
    0.00758645124733448,
    0.005281751975417137,
    -0.01911354251205921,
    -0.038313377648591995,
    -0.013051572255790234,
    0.006112306844443083,
    0.0018984104972332716,
    -0.020350385457277298,
    0.036357440054416656,
    -0.012763934209942818,
    -0.014784591272473335,
    -0.031093664467334747,
    0.020336003974080086,
    0.017387714236974716,
    -0.03871607035398483,
    0.025369668379426003,
    -0.013734712265431881,
    -0.03713406249880791,
    -0.01386414933949709,
    0.00202784757129848,
    0.015920761972665787,
    0.0557442381978035,
    0.002734358422458172,
    -0.0005923544522374868,
    0.017747262492775917,
    -0.0250676479190588,
    0.0014175157994031906,
    0.010139238089323044,
    -0.026664039120078087,
    -0.008614757098257542,
    0.07024119049310684,
    0.023773277178406715,
    -0.0027775040362030268,
    0.004134795628488064,
    0.005975678563117981,
    0.032129161059856415,
    -0.002430540742352605,
    -0.04317445680499077,
    0.004918609280139208,
    -0.015676269307732582,
    -0.04731644317507744,
    0.011857874691486359,
    -0.017847934737801552,
    -0.0054039983078837395,
    0.042743001133203506,
    0.020824987441301346,
    -0.004609398543834686,
    0.011901021003723145,
    -0.00502287782728672,
    -0.02803031913936138,
    -0.02079622447490692,
    -0.01734456978738308,
    -0.023500021547079086,
    0.02618943713605404,
    -0.02275216206908226,
    -0.0015586381778120995,
    -0.016941875219345093,
    0.00012157198216300458,
    0.027095496654510498,
    0.032330505549907684,
    0.003338398179039359,
    -0.003962212707847357,
    -0.019329270347952843,
    -0.0238164234906435,
    -0.0045015341602265835,
    0.02239261567592621,
    -0.005188269540667534,
    0.009305087849497795,
    -0.01573379710316658,
    -0.012893371284008026,
    0.01439628005027771,
    0.020048364996910095,
    -0.0017932428745552897,
    -0.02128520980477333,
    -0.0023244742769747972,
    -0.002000881591811776,
    -0.0010507773840799928,
    0.0282891932874918,
    -0.009039022959768772,
    -0.008909585885703564,
    0.018638940528035164,
    0.018495120108127594,
    0.001818411285057664,
    -0.02815975621342659,
    0.004835913423448801,
    0.007823752239346504,
    -0.013914486393332481,
    -0.010642604902386665,
    0.024348553270101547,
    -0.001700659398920834,
    0.009686208330094814,
    -0.001792344031855464,
    0.030489623546600342,
    0.028979524970054626,
    0.01151270978152752,
    0.005709613673388958,
    0.0017995350062847137,
    -0.004979731980711222,
    0.004023335874080658,
    -0.0021968348883092403,
    -0.015259194187819958,
    -0.048150595277547836,
    -0.006518595386296511,
    -0.05554288998246193,
    -0.016122108325362206,
    0.015633122995495796,
    -0.006701964419335127,
    -0.011153161525726318,
    -0.012224613688886166,
    0.033538587391376495,
    0.015259194187819958,
    -0.01812119223177433,
    0.009808454662561417,
    -0.013022808358073235,
    0.02723931521177292,
    -0.030317040160298347,
    0.014942792244255543,
    -0.010757659561932087,
    -0.034027568995952606,
    0.0005977476248517632,
    -0.002901547821238637,
    0.012138321995735168,
    0.02555663324892521,
    -0.0064287083223462105,
    -0.020666787400841713,
    -0.002969861961901188,
    -0.002721774158999324,
    0.011735628359019756,
    0.005810286849737167,
    0.003320420626550913,
    -0.008959922939538956,
    -0.024981357157230377,
    -0.012159895151853561,
    -0.022723399102687836,
    0.017718497663736343,
    -0.02521146647632122,
    0.08617633581161499,
    0.01077923271805048,
    -0.01953061670064926,
    -0.0076799336820840836,
    0.01734456978738308,
    0.004595016594976187,
    0.005547817330807447,
    -0.009830026887357235,
    -0.0003181994834449142,
    -0.05465121194720268,
    0.02991434745490551,
    -0.005238606594502926,
    -0.0327044352889061,
    -0.030863553285598755,
    0.00041347957449033856,
    -0.01137608103454113,
    0.016179636120796204,
    0.00909655075520277,
    -0.002924918429926038,
    -0.031553883105516434,
    0.024262262508273125,
    -0.007838134653866291,
    0.013353592716157436,
    0.008686666376888752,
    -0.011225071735680103,
    -0.005479502957314253,
    0.0042390646412968636,
    -0.006658818572759628,
    -0.018912196159362793,
    -0.04651105776429176,
    0.01826501078903675,
    -0.003057951107621193,
    -0.020393531769514084,
    -0.03940640017390251,
    0.0014283022610470653,
    -0.02893637865781784,
    0.0017438051290810108,
    -0.05085439234972,
    0.045044105499982834,
    -0.0026211009826511145,
    -0.00969339907169342,
    0.0342576801776886,
    -0.009046213701367378,
    -0.0013707746984437108,
    -0.0028673908673226833,
    0.002063802443444729,
    -0.010592267848551273,
    -0.010117664933204651,
    -0.03980909287929535
  ]
}